<?xml version="1.0" encoding="UTF-8"?>

<behavior name="JoyProto3">

	<executable package_path="sweetie_bot_flexbe_behaviors.joyproto3_sm" class="JoyProto3SM" />
	<tagstring>joystick, proto3</tagstring>
	<author>disRecord</author>
	<date>Sun Nov 18 2018</date>
	<description>
		Joystick based control for Proto3. Head petrforms random movements, also it position can be controlled by joystick. Different animation can be activated by joystick buttons or by TextCommand.
	</description>


	<!-- Contained Behaviors -->

	<!-- Available Parameters -->
	<params>

		<param type="text" name="action_list" default="greeting,head_shake,applause" label="action_list" hint="Sets the action_list" />

	</params>


</behavior>